Metadata-Version: 2.1
Name: SpeechRecognitionCover
Version: 1.0.3
Summary: Easy cover over SpeechRecognition
Author: Luka
Author-email: app6onpython@gmail.com
Keywords: SpeechRecognitionCover,Speech recognition cover
Classifier: Programming Language :: Python :: 3.9
